setup.py
src/digimat/__init__.py
src/digimat.ccme.egg-info/PKG-INFO
src/digimat.ccme.egg-info/SOURCES.txt
src/digimat.ccme.egg-info/dependency_links.txt
src/digimat.ccme.egg-info/namespace_packages.txt
src/digimat.ccme.egg-info/not-zip-safe
src/digimat.ccme.egg-info/requires.txt
src/digimat.ccme.egg-info/top_level.txt
src/digimat/ccme/__init__.py
src/digimat/ccme/ccme.py